{
  "data": [
    {
      "id": "ISA.5.1",
      "orgId": "ISA.5.1",
      "bookId": "ISA",
      "chapterId": "ISA.5",
      "bibleId": "de4e12af7f28f599-02",
      "reference": "Isaiah 5:1"
    },
    {
      "id": "ISA.5.2",
      "orgId": "ISA.5.2",
      "bookId": "ISA",
      "chapterId": "ISA.5",
      "bibleId": "de4e12af7f28f599-02",
      "reference": "Isaiah 5:2"
    },
    {
      "id": "ISA.5.3",
      "orgId": "ISA.5.3",
      "bookId": "ISA",
      "chapterId": "ISA.5",
      "bibleId": "de4e12af7f28f599-02",
      "reference": "Isaiah 5:3"
    },
    {
      "id": "ISA.5.4",
      "orgId": "ISA.5.4",
      "bookId": "ISA",
      "chapterId": "ISA.5",
      "bibleId": "de4e12af7f28f599-02",
      "reference": "Isaiah 5:4"
    },
    {
      "id": "ISA.5.5",
      "orgId": "ISA.5.5",
      "bookId": "ISA",
      "chapterId": "ISA.5",
      "bibleId": "de4e12af7f28f599-02",
      "reference": "Isaiah 5:5"
    },
    {
      "id": "ISA.5.6",
      "orgId": "ISA.5.6",
      "bookId": "ISA",
      "chapterId": "ISA.5",
      "bibleId": "de4e12af7f28f599-02",
      "reference": "Isaiah 5:6"
    },
    {
      "id": "ISA.5.7",
      "orgId": "ISA.5.7",
      "bookId": "ISA",
      "chapterId": "ISA.5",
      "bibleId": "de4e12af7f28f599-02",
      "reference": "Isaiah 5:7"
    },
    {
      "id": "ISA.5.8",
      "orgId": "ISA.5.8",
      "bookId": "ISA",
      "chapterId": "ISA.5",
      "bibleId": "de4e12af7f28f599-02",
      "reference": "Isaiah 5:8"
    },
    {
      "id": "ISA.5.9",
      "orgId": "ISA.5.9",
      "bookId": "ISA",
      "chapterId": "ISA.5",
      "bibleId": "de4e12af7f28f599-02",
      "reference": "Isaiah 5:9"
    },
    {
      "id": "ISA.5.10",
      "orgId": "ISA.5.10",
      "bookId": "ISA",
      "chapterId": "ISA.5",
      "bibleId": "de4e12af7f28f599-02",
      "reference": "Isaiah 5:10"
    },
    {
      "id": "ISA.5.11",
      "orgId": "ISA.5.11",
      "bookId": "ISA",
      "chapterId": "ISA.5",
      "bibleId": "de4e12af7f28f599-02",
      "reference": "Isaiah 5:11"
    },
    {
      "id": "ISA.5.12",
      "orgId": "ISA.5.12",
      "bookId": "ISA",
      "chapterId": "ISA.5",
      "bibleId": "de4e12af7f28f599-02",
      "reference": "Isaiah 5:12"
    },
    {
      "id": "ISA.5.13",
      "orgId": "ISA.5.13",
      "bookId": "ISA",
      "chapterId": "ISA.5",
      "bibleId": "de4e12af7f28f599-02",
      "reference": "Isaiah 5:13"
    },
    {
      "id": "ISA.5.14",
      "orgId": "ISA.5.14",
      "bookId": "ISA",
      "chapterId": "ISA.5",
      "bibleId": "de4e12af7f28f599-02",
      "reference": "Isaiah 5:14"
    },
    {
      "id": "ISA.5.15",
      "orgId": "ISA.5.15",
      "bookId": "ISA",
      "chapterId": "ISA.5",
      "bibleId": "de4e12af7f28f599-02",
      "reference": "Isaiah 5:15"
    },
    {
      "id": "ISA.5.16",
      "orgId": "ISA.5.16",
      "bookId": "ISA",
      "chapterId": "ISA.5",
      "bibleId": "de4e12af7f28f599-02",
      "reference": "Isaiah 5:16"
    },
    {
      "id": "ISA.5.17",
      "orgId": "ISA.5.17",
      "bookId": "ISA",
      "chapterId": "ISA.5",
      "bibleId": "de4e12af7f28f599-02",
      "reference": "Isaiah 5:17"
    },
    {
      "id": "ISA.5.18",
      "orgId": "ISA.5.18",
      "bookId": "ISA",
      "chapterId": "ISA.5",
      "bibleId": "de4e12af7f28f599-02",
      "reference": "Isaiah 5:18"
    },
    {
      "id": "ISA.5.19",
      "orgId": "ISA.5.19",
      "bookId": "ISA",
      "chapterId": "ISA.5",
      "bibleId": "de4e12af7f28f599-02",
      "reference": "Isaiah 5:19"
    },
    {
      "id": "ISA.5.20",
      "orgId": "ISA.5.20",
      "bookId": "ISA",
      "chapterId": "ISA.5",
      "bibleId": "de4e12af7f28f599-02",
      "reference": "Isaiah 5:20"
    },
    {
      "id": "ISA.5.21",
      "orgId": "ISA.5.21",
      "bookId": "ISA",
      "chapterId": "ISA.5",
      "bibleId": "de4e12af7f28f599-02",
      "reference": "Isaiah 5:21"
    },
    {
      "id": "ISA.5.22",
      "orgId": "ISA.5.22",
      "bookId": "ISA",
      "chapterId": "ISA.5",
      "bibleId": "de4e12af7f28f599-02",
      "reference": "Isaiah 5:22"
    },
    {
      "id": "ISA.5.23",
      "orgId": "ISA.5.23",
      "bookId": "ISA",
      "chapterId": "ISA.5",
      "bibleId": "de4e12af7f28f599-02",
      "reference": "Isaiah 5:23"
    },
    {
      "id": "ISA.5.24",
      "orgId": "ISA.5.24",
      "bookId": "ISA",
      "chapterId": "ISA.5",
      "bibleId": "de4e12af7f28f599-02",
      "reference": "Isaiah 5:24"
    },
    {
      "id": "ISA.5.25",
      "orgId": "ISA.5.25",
      "bookId": "ISA",
      "chapterId": "ISA.5",
      "bibleId": "de4e12af7f28f599-02",
      "reference": "Isaiah 5:25"
    },
    {
      "id": "ISA.5.26",
      "orgId": "ISA.5.26",
      "bookId": "ISA",
      "chapterId": "ISA.5",
      "bibleId": "de4e12af7f28f599-02",
      "reference": "Isaiah 5:26"
    },
    {
      "id": "ISA.5.27",
      "orgId": "ISA.5.27",
      "bookId": "ISA",
      "chapterId": "ISA.5",
      "bibleId": "de4e12af7f28f599-02",
      "reference": "Isaiah 5:27"
    },
    {
      "id": "ISA.5.28",
      "orgId": "ISA.5.28",
      "bookId": "ISA",
      "chapterId": "ISA.5",
      "bibleId": "de4e12af7f28f599-02",
      "reference": "Isaiah 5:28"
    },
    {
      "id": "ISA.5.29",
      "orgId": "ISA.5.29",
      "bookId": "ISA",
      "chapterId": "ISA.5",
      "bibleId": "de4e12af7f28f599-02",
      "reference": "Isaiah 5:29"
    },
    {
      "id": "ISA.5.30",
      "orgId": "ISA.5.30",
      "bookId": "ISA",
      "chapterId": "ISA.5",
      "bibleId": "de4e12af7f28f599-02",
      "reference": "Isaiah 5:30"
    }
  ]
}