{
  "data": {
    "id": "ISA.11.10",
    "orgId": "ISA.11.10",
    "bookId": "ISA",
    "chapterId": "ISA.11",
    "bibleId": "de4e12af7f28f599-02",
    "reference": "Isaiah 11:10",
    "content": "<p class=\"p\"><span data-number=\"10\" data-sid=\"ISA 11:10\" class=\"v\">10</span>¶ And in that day there shall be a root of Jesse, which shall stand for an ensign of the people; to it shall the Gentiles seek: and his rest shall be glorious. </p>",
    "verseCount": 1,
    "copyright": "\n          \n            PUBLIC DOMAIN except in the United Kingdom, where a Crown Copyright applies to printing the KJV. See http://www.cambridge.org/about-us/who-we-are/queens-printers-patent\n        ",
    "next": {
      "id": "ISA.11.11",
      "number": "11"
    },
    "previous": {
      "id": "ISA.11.9",
      "number": "9"
    }
  },
  "meta": {
    "fums": "<script>\nvar _BAPI=_BAPI||{};\nif(typeof(_BAPI.t)==='undefined'){\ndocument.write('\\x3Cscript src=\"'+document.location.protocol+'//cdn.scripture.api.bible/fums/fumsv2.min.js\"\\x3E\\x3C/script\\x3E');}\ndocument.write(\"\\x3Cscript\\x3E_BAPI.t('7ebb3ab4-27e7-4680-b20e-01a89968ffc5');\\x3C/script\\x3E\");\n</script><noscript><img src=\"https://d3a2okcloueqyx.cloudfront.net/nf1?t='7ebb3ab4-27e7-4680-b20e-01a89968ffc5'\" height=\"1\" width=\"1\" border=\"0\" alt=\"\" style=\"height: 0; width: 0;\" /></noscript>",
    "fumsId": "7ebb3ab4-27e7-4680-b20e-01a89968ffc5",
    "fumsJsInclude": "cdn.scripture.api.bible/fums/fumsv2.min.js",
    "fumsJs": "var _BAPI=_BAPI||{};if(typeof(_BAPI.t)!='undefined'){ _BAPI.t('7ebb3ab4-27e7-4680-b20e-01a89968ffc5'); }",
    "fumsNoScript": "<img src=\"https://d3btgtzu3ctdwx.cloudfront.net/nf1?t=7ebb3ab4-27e7-4680-b20e-01a89968ffc5\" height=\"1\" width=\"1\" border=\"0\" alt=\"\" style=\"height: 0; width: 0;\" />"
  }
}