{
  "data": {
    "id": "PSA.37.34",
    "orgId": "PSA.37.34",
    "bookId": "PSA",
    "chapterId": "PSA.37",
    "bibleId": "de4e12af7f28f599-02",
    "reference": "Psalms 37:34",
    "content": "<p class=\"b\"></p><p class=\"q1\"><span data-number=\"34\" data-sid=\"PSA 37:34\" class=\"v\">34</span>Wait on the <span class=\"nd\">LORD</span>, and keep his way, and he shall exalt thee to inherit the land: when the wicked are cut off, thou shalt see <span class=\"add\">it</span>.</p>",
    "verseCount": 1,
    "copyright": "\n          \n            PUBLIC DOMAIN except in the United Kingdom, where a Crown Copyright applies to printing the KJV. See http://www.cambridge.org/about-us/who-we-are/queens-printers-patent\n        ",
    "next": {
      "id": "PSA.37.35",
      "number": "35"
    },
    "previous": {
      "id": "PSA.37.33",
      "number": "33"
    }
  },
  "meta": {
    "fums": "<script>\nvar _BAPI=_BAPI||{};\nif(typeof(_BAPI.t)==='undefined'){\ndocument.write('\\x3Cscript src=\"'+document.location.protocol+'//cdn.scripture.api.bible/fums/fumsv2.min.js\"\\x3E\\x3C/script\\x3E');}\ndocument.write(\"\\x3Cscript\\x3E_BAPI.t('3e4f63c2-2af5-4dfc-af47-dedc3acc5fb2');\\x3C/script\\x3E\");\n</script><noscript><img src=\"https://d3a2okcloueqyx.cloudfront.net/nf1?t='3e4f63c2-2af5-4dfc-af47-dedc3acc5fb2'\" height=\"1\" width=\"1\" border=\"0\" alt=\"\" style=\"height: 0; width: 0;\" /></noscript>",
    "fumsId": "3e4f63c2-2af5-4dfc-af47-dedc3acc5fb2",
    "fumsJsInclude": "cdn.scripture.api.bible/fums/fumsv2.min.js",
    "fumsJs": "var _BAPI=_BAPI||{};if(typeof(_BAPI.t)!='undefined'){ _BAPI.t('3e4f63c2-2af5-4dfc-af47-dedc3acc5fb2'); }",
    "fumsNoScript": "<img src=\"https://d3btgtzu3ctdwx.cloudfront.net/nf1?t=3e4f63c2-2af5-4dfc-af47-dedc3acc5fb2\" height=\"1\" width=\"1\" border=\"0\" alt=\"\" style=\"height: 0; width: 0;\" />"
  }
}