{
  "data": [
    {
      "id": "JER.10.1",
      "orgId": "JER.10.1",
      "bookId": "JER",
      "chapterId": "JER.10",
      "bibleId": "de4e12af7f28f599-02",
      "reference": "Jeremiah 10:1"
    },
    {
      "id": "JER.10.2",
      "orgId": "JER.10.2",
      "bookId": "JER",
      "chapterId": "JER.10",
      "bibleId": "de4e12af7f28f599-02",
      "reference": "Jeremiah 10:2"
    },
    {
      "id": "JER.10.3",
      "orgId": "JER.10.3",
      "bookId": "JER",
      "chapterId": "JER.10",
      "bibleId": "de4e12af7f28f599-02",
      "reference": "Jeremiah 10:3"
    },
    {
      "id": "JER.10.4",
      "orgId": "JER.10.4",
      "bookId": "JER",
      "chapterId": "JER.10",
      "bibleId": "de4e12af7f28f599-02",
      "reference": "Jeremiah 10:4"
    },
    {
      "id": "JER.10.5",
      "orgId": "JER.10.5",
      "bookId": "JER",
      "chapterId": "JER.10",
      "bibleId": "de4e12af7f28f599-02",
      "reference": "Jeremiah 10:5"
    },
    {
      "id": "JER.10.6",
      "orgId": "JER.10.6",
      "bookId": "JER",
      "chapterId": "JER.10",
      "bibleId": "de4e12af7f28f599-02",
      "reference": "Jeremiah 10:6"
    },
    {
      "id": "JER.10.7",
      "orgId": "JER.10.7",
      "bookId": "JER",
      "chapterId": "JER.10",
      "bibleId": "de4e12af7f28f599-02",
      "reference": "Jeremiah 10:7"
    },
    {
      "id": "JER.10.8",
      "orgId": "JER.10.8",
      "bookId": "JER",
      "chapterId": "JER.10",
      "bibleId": "de4e12af7f28f599-02",
      "reference": "Jeremiah 10:8"
    },
    {
      "id": "JER.10.9",
      "orgId": "JER.10.9",
      "bookId": "JER",
      "chapterId": "JER.10",
      "bibleId": "de4e12af7f28f599-02",
      "reference": "Jeremiah 10:9"
    },
    {
      "id": "JER.10.10",
      "orgId": "JER.10.10",
      "bookId": "JER",
      "chapterId": "JER.10",
      "bibleId": "de4e12af7f28f599-02",
      "reference": "Jeremiah 10:10"
    },
    {
      "id": "JER.10.11",
      "orgId": "JER.10.11",
      "bookId": "JER",
      "chapterId": "JER.10",
      "bibleId": "de4e12af7f28f599-02",
      "reference": "Jeremiah 10:11"
    },
    {
      "id": "JER.10.12",
      "orgId": "JER.10.12",
      "bookId": "JER",
      "chapterId": "JER.10",
      "bibleId": "de4e12af7f28f599-02",
      "reference": "Jeremiah 10:12"
    },
    {
      "id": "JER.10.13",
      "orgId": "JER.10.13",
      "bookId": "JER",
      "chapterId": "JER.10",
      "bibleId": "de4e12af7f28f599-02",
      "reference": "Jeremiah 10:13"
    },
    {
      "id": "JER.10.14",
      "orgId": "JER.10.14",
      "bookId": "JER",
      "chapterId": "JER.10",
      "bibleId": "de4e12af7f28f599-02",
      "reference": "Jeremiah 10:14"
    },
    {
      "id": "JER.10.15",
      "orgId": "JER.10.15",
      "bookId": "JER",
      "chapterId": "JER.10",
      "bibleId": "de4e12af7f28f599-02",
      "reference": "Jeremiah 10:15"
    },
    {
      "id": "JER.10.16",
      "orgId": "JER.10.16",
      "bookId": "JER",
      "chapterId": "JER.10",
      "bibleId": "de4e12af7f28f599-02",
      "reference": "Jeremiah 10:16"
    },
    {
      "id": "JER.10.17",
      "orgId": "JER.10.17",
      "bookId": "JER",
      "chapterId": "JER.10",
      "bibleId": "de4e12af7f28f599-02",
      "reference": "Jeremiah 10:17"
    },
    {
      "id": "JER.10.18",
      "orgId": "JER.10.18",
      "bookId": "JER",
      "chapterId": "JER.10",
      "bibleId": "de4e12af7f28f599-02",
      "reference": "Jeremiah 10:18"
    },
    {
      "id": "JER.10.19",
      "orgId": "JER.10.19",
      "bookId": "JER",
      "chapterId": "JER.10",
      "bibleId": "de4e12af7f28f599-02",
      "reference": "Jeremiah 10:19"
    },
    {
      "id": "JER.10.20",
      "orgId": "JER.10.20",
      "bookId": "JER",
      "chapterId": "JER.10",
      "bibleId": "de4e12af7f28f599-02",
      "reference": "Jeremiah 10:20"
    },
    {
      "id": "JER.10.21",
      "orgId": "JER.10.21",
      "bookId": "JER",
      "chapterId": "JER.10",
      "bibleId": "de4e12af7f28f599-02",
      "reference": "Jeremiah 10:21"
    },
    {
      "id": "JER.10.22",
      "orgId": "JER.10.22",
      "bookId": "JER",
      "chapterId": "JER.10",
      "bibleId": "de4e12af7f28f599-02",
      "reference": "Jeremiah 10:22"
    },
    {
      "id": "JER.10.23",
      "orgId": "JER.10.23",
      "bookId": "JER",
      "chapterId": "JER.10",
      "bibleId": "de4e12af7f28f599-02",
      "reference": "Jeremiah 10:23"
    },
    {
      "id": "JER.10.24",
      "orgId": "JER.10.24",
      "bookId": "JER",
      "chapterId": "JER.10",
      "bibleId": "de4e12af7f28f599-02",
      "reference": "Jeremiah 10:24"
    },
    {
      "id": "JER.10.25",
      "orgId": "JER.10.25",
      "bookId": "JER",
      "chapterId": "JER.10",
      "bibleId": "de4e12af7f28f599-02",
      "reference": "Jeremiah 10:25"
    }
  ]
}