{
  "data": {
    "id": "JOS.14.2",
    "orgId": "JOS.14.2",
    "bookId": "JOS",
    "chapterId": "JOS.14",
    "bibleId": "de4e12af7f28f599-02",
    "reference": "Joshua 14:2",
    "content": "<p class=\"p\"><span data-number=\"2\" data-sid=\"JOS 14:2\" class=\"v\">2</span>By lot <span class=\"add\">was</span> their inheritance, as the <span class=\"nd\">LORD</span> commanded by the hand of Moses, for the nine tribes, and <span class=\"add\">for</span> the half tribe. </p>",
    "verseCount": 1,
    "copyright": "\n          \n            PUBLIC DOMAIN except in the United Kingdom, where a Crown Copyright applies to printing the KJV. See http://www.cambridge.org/about-us/who-we-are/queens-printers-patent\n        ",
    "next": {
      "id": "JOS.14.3",
      "number": "3"
    },
    "previous": {
      "id": "JOS.14.1",
      "number": "1"
    }
  },
  "meta": {
    "fums": "<script>\nvar _BAPI=_BAPI||{};\nif(typeof(_BAPI.t)==='undefined'){\ndocument.write('\\x3Cscript src=\"'+document.location.protocol+'//cdn.scripture.api.bible/fums/fumsv2.min.js\"\\x3E\\x3C/script\\x3E');}\ndocument.write(\"\\x3Cscript\\x3E_BAPI.t('852da6fd-f41d-40ba-b3d4-2b65b7b8365d');\\x3C/script\\x3E\");\n</script><noscript><img src=\"https://d3a2okcloueqyx.cloudfront.net/nf1?t='852da6fd-f41d-40ba-b3d4-2b65b7b8365d'\" height=\"1\" width=\"1\" border=\"0\" alt=\"\" style=\"height: 0; width: 0;\" /></noscript>",
    "fumsId": "852da6fd-f41d-40ba-b3d4-2b65b7b8365d",
    "fumsJsInclude": "cdn.scripture.api.bible/fums/fumsv2.min.js",
    "fumsJs": "var _BAPI=_BAPI||{};if(typeof(_BAPI.t)!='undefined'){ _BAPI.t('852da6fd-f41d-40ba-b3d4-2b65b7b8365d'); }",
    "fumsNoScript": "<img src=\"https://d3btgtzu3ctdwx.cloudfront.net/nf1?t=852da6fd-f41d-40ba-b3d4-2b65b7b8365d\" height=\"1\" width=\"1\" border=\"0\" alt=\"\" style=\"height: 0; width: 0;\" />"
  }
}