{
  "data": {
    "id": "NUM.31.47",
    "orgId": "NUM.31.47",
    "bookId": "NUM",
    "chapterId": "NUM.31",
    "bibleId": "de4e12af7f28f599-02",
    "reference": "Numbers 31:47",
    "content": "<p class=\"p\"><span data-number=\"47\" data-sid=\"NUM 31:47\" class=\"v\">47</span>Even of the children of Israel’s half, Moses took one portion of fifty, <span class=\"add\">both</span> of man and of beast, and gave them unto the Levites, which kept the charge of the tabernacle of the <span class=\"nd\">LORD</span>; as the <span class=\"nd\">LORD</span> commanded Moses.</p>",
    "verseCount": 1,
    "copyright": "\n          \n            PUBLIC DOMAIN except in the United Kingdom, where a Crown Copyright applies to printing the KJV. See http://www.cambridge.org/about-us/who-we-are/queens-printers-patent\n        ",
    "next": {
      "id": "NUM.31.48",
      "number": "48"
    },
    "previous": {
      "id": "NUM.31.46",
      "number": "46"
    }
  },
  "meta": {
    "fums": "<script>\nvar _BAPI=_BAPI||{};\nif(typeof(_BAPI.t)==='undefined'){\ndocument.write('\\x3Cscript src=\"'+document.location.protocol+'//cdn.scripture.api.bible/fums/fumsv2.min.js\"\\x3E\\x3C/script\\x3E');}\ndocument.write(\"\\x3Cscript\\x3E_BAPI.t('8621a4fc-84a1-4a45-bd23-516162ec2424');\\x3C/script\\x3E\");\n</script><noscript><img src=\"https://d3a2okcloueqyx.cloudfront.net/nf1?t='8621a4fc-84a1-4a45-bd23-516162ec2424'\" height=\"1\" width=\"1\" border=\"0\" alt=\"\" style=\"height: 0; width: 0;\" /></noscript>",
    "fumsId": "8621a4fc-84a1-4a45-bd23-516162ec2424",
    "fumsJsInclude": "cdn.scripture.api.bible/fums/fumsv2.min.js",
    "fumsJs": "var _BAPI=_BAPI||{};if(typeof(_BAPI.t)!='undefined'){ _BAPI.t('8621a4fc-84a1-4a45-bd23-516162ec2424'); }",
    "fumsNoScript": "<img src=\"https://d3btgtzu3ctdwx.cloudfront.net/nf1?t=8621a4fc-84a1-4a45-bd23-516162ec2424\" height=\"1\" width=\"1\" border=\"0\" alt=\"\" style=\"height: 0; width: 0;\" />"
  }
}