{
  "data": {
    "id": "COL.2.2",
    "orgId": "COL.2.2",
    "bookId": "COL",
    "chapterId": "COL.2",
    "bibleId": "de4e12af7f28f599-02",
    "reference": "Colossians 2:2",
    "content": "<p class=\"p\"><span data-number=\"2\" data-sid=\"COL 2:2\" class=\"v\">2</span>That their hearts might be comforted, being knit together in love, and unto all riches of the full assurance of understanding, to the acknowledgement of the mystery of God, and of the Father, and of Christ; </p>",
    "verseCount": 1,
    "copyright": "\n          \n            PUBLIC DOMAIN except in the United Kingdom, where a Crown Copyright applies to printing the KJV. See http://www.cambridge.org/about-us/who-we-are/queens-printers-patent\n        ",
    "next": {
      "id": "COL.2.3",
      "number": "3"
    },
    "previous": {
      "id": "COL.2.1",
      "number": "1"
    }
  },
  "meta": {
    "fums": "<script>\nvar _BAPI=_BAPI||{};\nif(typeof(_BAPI.t)==='undefined'){\ndocument.write('\\x3Cscript src=\"'+document.location.protocol+'//cdn.scripture.api.bible/fums/fumsv2.min.js\"\\x3E\\x3C/script\\x3E');}\ndocument.write(\"\\x3Cscript\\x3E_BAPI.t('feb2a225-afbd-4692-a738-14d2e7daf75b');\\x3C/script\\x3E\");\n</script><noscript><img src=\"https://d3a2okcloueqyx.cloudfront.net/nf1?t='feb2a225-afbd-4692-a738-14d2e7daf75b'\" height=\"1\" width=\"1\" border=\"0\" alt=\"\" style=\"height: 0; width: 0;\" /></noscript>",
    "fumsId": "feb2a225-afbd-4692-a738-14d2e7daf75b",
    "fumsJsInclude": "cdn.scripture.api.bible/fums/fumsv2.min.js",
    "fumsJs": "var _BAPI=_BAPI||{};if(typeof(_BAPI.t)!='undefined'){ _BAPI.t('feb2a225-afbd-4692-a738-14d2e7daf75b'); }",
    "fumsNoScript": "<img src=\"https://d3btgtzu3ctdwx.cloudfront.net/nf1?t=feb2a225-afbd-4692-a738-14d2e7daf75b\" height=\"1\" width=\"1\" border=\"0\" alt=\"\" style=\"height: 0; width: 0;\" />"
  }
}