{
  "data": [
    {
      "id": "PRO.10.1",
      "orgId": "PRO.10.1",
      "bookId": "PRO",
      "chapterId": "PRO.10",
      "bibleId": "de4e12af7f28f599-02",
      "reference": "Proverbs 10:1"
    },
    {
      "id": "PRO.10.2",
      "orgId": "PRO.10.2",
      "bookId": "PRO",
      "chapterId": "PRO.10",
      "bibleId": "de4e12af7f28f599-02",
      "reference": "Proverbs 10:2"
    },
    {
      "id": "PRO.10.3",
      "orgId": "PRO.10.3",
      "bookId": "PRO",
      "chapterId": "PRO.10",
      "bibleId": "de4e12af7f28f599-02",
      "reference": "Proverbs 10:3"
    },
    {
      "id": "PRO.10.4",
      "orgId": "PRO.10.4",
      "bookId": "PRO",
      "chapterId": "PRO.10",
      "bibleId": "de4e12af7f28f599-02",
      "reference": "Proverbs 10:4"
    },
    {
      "id": "PRO.10.5",
      "orgId": "PRO.10.5",
      "bookId": "PRO",
      "chapterId": "PRO.10",
      "bibleId": "de4e12af7f28f599-02",
      "reference": "Proverbs 10:5"
    },
    {
      "id": "PRO.10.6",
      "orgId": "PRO.10.6",
      "bookId": "PRO",
      "chapterId": "PRO.10",
      "bibleId": "de4e12af7f28f599-02",
      "reference": "Proverbs 10:6"
    },
    {
      "id": "PRO.10.7",
      "orgId": "PRO.10.7",
      "bookId": "PRO",
      "chapterId": "PRO.10",
      "bibleId": "de4e12af7f28f599-02",
      "reference": "Proverbs 10:7"
    },
    {
      "id": "PRO.10.8",
      "orgId": "PRO.10.8",
      "bookId": "PRO",
      "chapterId": "PRO.10",
      "bibleId": "de4e12af7f28f599-02",
      "reference": "Proverbs 10:8"
    },
    {
      "id": "PRO.10.9",
      "orgId": "PRO.10.9",
      "bookId": "PRO",
      "chapterId": "PRO.10",
      "bibleId": "de4e12af7f28f599-02",
      "reference": "Proverbs 10:9"
    },
    {
      "id": "PRO.10.10",
      "orgId": "PRO.10.10",
      "bookId": "PRO",
      "chapterId": "PRO.10",
      "bibleId": "de4e12af7f28f599-02",
      "reference": "Proverbs 10:10"
    },
    {
      "id": "PRO.10.11",
      "orgId": "PRO.10.11",
      "bookId": "PRO",
      "chapterId": "PRO.10",
      "bibleId": "de4e12af7f28f599-02",
      "reference": "Proverbs 10:11"
    },
    {
      "id": "PRO.10.12",
      "orgId": "PRO.10.12",
      "bookId": "PRO",
      "chapterId": "PRO.10",
      "bibleId": "de4e12af7f28f599-02",
      "reference": "Proverbs 10:12"
    },
    {
      "id": "PRO.10.13",
      "orgId": "PRO.10.13",
      "bookId": "PRO",
      "chapterId": "PRO.10",
      "bibleId": "de4e12af7f28f599-02",
      "reference": "Proverbs 10:13"
    },
    {
      "id": "PRO.10.14",
      "orgId": "PRO.10.14",
      "bookId": "PRO",
      "chapterId": "PRO.10",
      "bibleId": "de4e12af7f28f599-02",
      "reference": "Proverbs 10:14"
    },
    {
      "id": "PRO.10.15",
      "orgId": "PRO.10.15",
      "bookId": "PRO",
      "chapterId": "PRO.10",
      "bibleId": "de4e12af7f28f599-02",
      "reference": "Proverbs 10:15"
    },
    {
      "id": "PRO.10.16",
      "orgId": "PRO.10.16",
      "bookId": "PRO",
      "chapterId": "PRO.10",
      "bibleId": "de4e12af7f28f599-02",
      "reference": "Proverbs 10:16"
    },
    {
      "id": "PRO.10.17",
      "orgId": "PRO.10.17",
      "bookId": "PRO",
      "chapterId": "PRO.10",
      "bibleId": "de4e12af7f28f599-02",
      "reference": "Proverbs 10:17"
    },
    {
      "id": "PRO.10.18",
      "orgId": "PRO.10.18",
      "bookId": "PRO",
      "chapterId": "PRO.10",
      "bibleId": "de4e12af7f28f599-02",
      "reference": "Proverbs 10:18"
    },
    {
      "id": "PRO.10.19",
      "orgId": "PRO.10.19",
      "bookId": "PRO",
      "chapterId": "PRO.10",
      "bibleId": "de4e12af7f28f599-02",
      "reference": "Proverbs 10:19"
    },
    {
      "id": "PRO.10.20",
      "orgId": "PRO.10.20",
      "bookId": "PRO",
      "chapterId": "PRO.10",
      "bibleId": "de4e12af7f28f599-02",
      "reference": "Proverbs 10:20"
    },
    {
      "id": "PRO.10.21",
      "orgId": "PRO.10.21",
      "bookId": "PRO",
      "chapterId": "PRO.10",
      "bibleId": "de4e12af7f28f599-02",
      "reference": "Proverbs 10:21"
    },
    {
      "id": "PRO.10.22",
      "orgId": "PRO.10.22",
      "bookId": "PRO",
      "chapterId": "PRO.10",
      "bibleId": "de4e12af7f28f599-02",
      "reference": "Proverbs 10:22"
    },
    {
      "id": "PRO.10.23",
      "orgId": "PRO.10.23",
      "bookId": "PRO",
      "chapterId": "PRO.10",
      "bibleId": "de4e12af7f28f599-02",
      "reference": "Proverbs 10:23"
    },
    {
      "id": "PRO.10.24",
      "orgId": "PRO.10.24",
      "bookId": "PRO",
      "chapterId": "PRO.10",
      "bibleId": "de4e12af7f28f599-02",
      "reference": "Proverbs 10:24"
    },
    {
      "id": "PRO.10.25",
      "orgId": "PRO.10.25",
      "bookId": "PRO",
      "chapterId": "PRO.10",
      "bibleId": "de4e12af7f28f599-02",
      "reference": "Proverbs 10:25"
    },
    {
      "id": "PRO.10.26",
      "orgId": "PRO.10.26",
      "bookId": "PRO",
      "chapterId": "PRO.10",
      "bibleId": "de4e12af7f28f599-02",
      "reference": "Proverbs 10:26"
    },
    {
      "id": "PRO.10.27",
      "orgId": "PRO.10.27",
      "bookId": "PRO",
      "chapterId": "PRO.10",
      "bibleId": "de4e12af7f28f599-02",
      "reference": "Proverbs 10:27"
    },
    {
      "id": "PRO.10.28",
      "orgId": "PRO.10.28",
      "bookId": "PRO",
      "chapterId": "PRO.10",
      "bibleId": "de4e12af7f28f599-02",
      "reference": "Proverbs 10:28"
    },
    {
      "id": "PRO.10.29",
      "orgId": "PRO.10.29",
      "bookId": "PRO",
      "chapterId": "PRO.10",
      "bibleId": "de4e12af7f28f599-02",
      "reference": "Proverbs 10:29"
    },
    {
      "id": "PRO.10.30",
      "orgId": "PRO.10.30",
      "bookId": "PRO",
      "chapterId": "PRO.10",
      "bibleId": "de4e12af7f28f599-02",
      "reference": "Proverbs 10:30"
    },
    {
      "id": "PRO.10.31",
      "orgId": "PRO.10.31",
      "bookId": "PRO",
      "chapterId": "PRO.10",
      "bibleId": "de4e12af7f28f599-02",
      "reference": "Proverbs 10:31"
    },
    {
      "id": "PRO.10.32",
      "orgId": "PRO.10.32",
      "bookId": "PRO",
      "chapterId": "PRO.10",
      "bibleId": "de4e12af7f28f599-02",
      "reference": "Proverbs 10:32"
    }
  ]
}