{
  "data": {
    "id": "ISA.43.9",
    "orgId": "ISA.43.9",
    "bookId": "ISA",
    "chapterId": "ISA.43",
    "bibleId": "de4e12af7f28f599-02",
    "reference": "Isaiah 43:9",
    "content": "<p class=\"p\"><span data-number=\"9\" data-sid=\"ISA 43:9\" class=\"v\">9</span>Let all the nations be gathered together, and let the people be assembled: who among them can declare this, and shew us former things? let them bring forth their witnesses, that they may be justified: or let them hear, and say, <span class=\"add\">It is</span> truth. </p>",
    "verseCount": 1,
    "copyright": "\n          \n            PUBLIC DOMAIN except in the United Kingdom, where a Crown Copyright applies to printing the KJV. See http://www.cambridge.org/about-us/who-we-are/queens-printers-patent\n        ",
    "next": {
      "id": "ISA.43.10",
      "number": "10"
    },
    "previous": {
      "id": "ISA.43.8",
      "number": "8"
    }
  },
  "meta": {
    "fums": "<script>\nvar _BAPI=_BAPI||{};\nif(typeof(_BAPI.t)==='undefined'){\ndocument.write('\\x3Cscript src=\"'+document.location.protocol+'//cdn.scripture.api.bible/fums/fumsv2.min.js\"\\x3E\\x3C/script\\x3E');}\ndocument.write(\"\\x3Cscript\\x3E_BAPI.t('c98205d6-76ca-472b-8439-40a56a10e461');\\x3C/script\\x3E\");\n</script><noscript><img src=\"https://d3a2okcloueqyx.cloudfront.net/nf1?t='c98205d6-76ca-472b-8439-40a56a10e461'\" height=\"1\" width=\"1\" border=\"0\" alt=\"\" style=\"height: 0; width: 0;\" /></noscript>",
    "fumsId": "c98205d6-76ca-472b-8439-40a56a10e461",
    "fumsJsInclude": "cdn.scripture.api.bible/fums/fumsv2.min.js",
    "fumsJs": "var _BAPI=_BAPI||{};if(typeof(_BAPI.t)!='undefined'){ _BAPI.t('c98205d6-76ca-472b-8439-40a56a10e461'); }",
    "fumsNoScript": "<img src=\"https://d3btgtzu3ctdwx.cloudfront.net/nf1?t=c98205d6-76ca-472b-8439-40a56a10e461\" height=\"1\" width=\"1\" border=\"0\" alt=\"\" style=\"height: 0; width: 0;\" />"
  }
}