{
  "data": {
    "id": "PSA.119.145",
    "orgId": "PSA.119.145",
    "bookId": "PSA",
    "chapterId": "PSA.119",
    "bibleId": "de4e12af7f28f599-02",
    "reference": "Psalms 119:145",
    "content": "<p class=\"b\"></p><p class=\"s1\"><span class=\"tl\">ק KOPH.</span></p><p class=\"q1\"><span data-number=\"145\" data-sid=\"PSA 119:145\" class=\"v\">145</span>I cried with <span class=\"add\">my</span> whole heart; hear me, O <span class=\"nd\">LORD</span>: I will keep thy statutes.</p>",
    "verseCount": 1,
    "copyright": "\n          \n            PUBLIC DOMAIN except in the United Kingdom, where a Crown Copyright applies to printing the KJV. See http://www.cambridge.org/about-us/who-we-are/queens-printers-patent\n        ",
    "next": {
      "id": "PSA.119.146",
      "number": "146"
    },
    "previous": {
      "id": "PSA.119.144",
      "number": "144"
    }
  },
  "meta": {
    "fums": "<script>\nvar _BAPI=_BAPI||{};\nif(typeof(_BAPI.t)==='undefined'){\ndocument.write('\\x3Cscript src=\"'+document.location.protocol+'//cdn.scripture.api.bible/fums/fumsv2.min.js\"\\x3E\\x3C/script\\x3E');}\ndocument.write(\"\\x3Cscript\\x3E_BAPI.t('49b3f3b7-4755-4e6d-a8f1-8bd6b2e726ca');\\x3C/script\\x3E\");\n</script><noscript><img src=\"https://d3a2okcloueqyx.cloudfront.net/nf1?t='49b3f3b7-4755-4e6d-a8f1-8bd6b2e726ca'\" height=\"1\" width=\"1\" border=\"0\" alt=\"\" style=\"height: 0; width: 0;\" /></noscript>",
    "fumsId": "49b3f3b7-4755-4e6d-a8f1-8bd6b2e726ca",
    "fumsJsInclude": "cdn.scripture.api.bible/fums/fumsv2.min.js",
    "fumsJs": "var _BAPI=_BAPI||{};if(typeof(_BAPI.t)!='undefined'){ _BAPI.t('49b3f3b7-4755-4e6d-a8f1-8bd6b2e726ca'); }",
    "fumsNoScript": "<img src=\"https://d3btgtzu3ctdwx.cloudfront.net/nf1?t=49b3f3b7-4755-4e6d-a8f1-8bd6b2e726ca\" height=\"1\" width=\"1\" border=\"0\" alt=\"\" style=\"height: 0; width: 0;\" />"
  }
}