{
  "data": {
    "id": "GEN.1.20",
    "orgId": "GEN.1.20",
    "bookId": "GEN",
    "chapterId": "GEN.1",
    "bibleId": "de4e12af7f28f599-02",
    "reference": "Genesis 1:20",
    "content": "<p class=\"p\"><span data-number=\"20\" data-sid=\"GEN 1:20\" class=\"v\">20</span>And God said, Let the waters bring forth abundantly the moving creature that hath life, and fowl <span class=\"add\">that</span> may fly above the earth in the open firmament of heaven. </p>",
    "verseCount": 1,
    "copyright": "\n          \n            PUBLIC DOMAIN except in the United Kingdom, where a Crown Copyright applies to printing the KJV. See http://www.cambridge.org/about-us/who-we-are/queens-printers-patent\n        ",
    "next": {
      "id": "GEN.1.21",
      "number": "21"
    },
    "previous": {
      "id": "GEN.1.19",
      "number": "19"
    }
  },
  "meta": {
    "fums": "<script>\nvar _BAPI=_BAPI||{};\nif(typeof(_BAPI.t)==='undefined'){\ndocument.write('\\x3Cscript src=\"'+document.location.protocol+'//cdn.scripture.api.bible/fums/fumsv2.min.js\"\\x3E\\x3C/script\\x3E');}\ndocument.write(\"\\x3Cscript\\x3E_BAPI.t('ee5a6051-f578-47d8-b3ef-ddb61d09d8a5');\\x3C/script\\x3E\");\n</script><noscript><img src=\"https://d3a2okcloueqyx.cloudfront.net/nf1?t='ee5a6051-f578-47d8-b3ef-ddb61d09d8a5'\" height=\"1\" width=\"1\" border=\"0\" alt=\"\" style=\"height: 0; width: 0;\" /></noscript>",
    "fumsId": "ee5a6051-f578-47d8-b3ef-ddb61d09d8a5",
    "fumsJsInclude": "cdn.scripture.api.bible/fums/fumsv2.min.js",
    "fumsJs": "var _BAPI=_BAPI||{};if(typeof(_BAPI.t)!='undefined'){ _BAPI.t('ee5a6051-f578-47d8-b3ef-ddb61d09d8a5'); }",
    "fumsNoScript": "<img src=\"https://d3btgtzu3ctdwx.cloudfront.net/nf1?t=ee5a6051-f578-47d8-b3ef-ddb61d09d8a5\" height=\"1\" width=\"1\" border=\"0\" alt=\"\" style=\"height: 0; width: 0;\" />"
  }
}