{
  "data": {
    "id": "GEN.44.1",
    "orgId": "GEN.44.1",
    "bookId": "GEN",
    "chapterId": "GEN.44",
    "bibleId": "de4e12af7f28f599-02",
    "reference": "Genesis 44:1",
    "content": "<p class=\"p\"><span data-number=\"1\" data-sid=\"GEN 44:1\" class=\"v\">1</span>And he commanded the steward of his house, saying, Fill the men’s sacks <span class=\"add\">with</span> food, as much as they can carry, and put every man’s money in his sack’s mouth. </p>",
    "verseCount": 1,
    "copyright": "\n          \n            PUBLIC DOMAIN except in the United Kingdom, where a Crown Copyright applies to printing the KJV. See http://www.cambridge.org/about-us/who-we-are/queens-printers-patent\n        ",
    "next": {
      "id": "GEN.44.2",
      "number": "2"
    },
    "previous": {
      "id": "GEN.43.34",
      "number": "34"
    }
  },
  "meta": {
    "fums": "<script>\nvar _BAPI=_BAPI||{};\nif(typeof(_BAPI.t)==='undefined'){\ndocument.write('\\x3Cscript src=\"'+document.location.protocol+'//cdn.scripture.api.bible/fums/fumsv2.min.js\"\\x3E\\x3C/script\\x3E');}\ndocument.write(\"\\x3Cscript\\x3E_BAPI.t('8d43f76e-8b36-4a6b-9689-ff6ace3d584e');\\x3C/script\\x3E\");\n</script><noscript><img src=\"https://d3a2okcloueqyx.cloudfront.net/nf1?t='8d43f76e-8b36-4a6b-9689-ff6ace3d584e'\" height=\"1\" width=\"1\" border=\"0\" alt=\"\" style=\"height: 0; width: 0;\" /></noscript>",
    "fumsId": "8d43f76e-8b36-4a6b-9689-ff6ace3d584e",
    "fumsJsInclude": "cdn.scripture.api.bible/fums/fumsv2.min.js",
    "fumsJs": "var _BAPI=_BAPI||{};if(typeof(_BAPI.t)!='undefined'){ _BAPI.t('8d43f76e-8b36-4a6b-9689-ff6ace3d584e'); }",
    "fumsNoScript": "<img src=\"https://d3btgtzu3ctdwx.cloudfront.net/nf1?t=8d43f76e-8b36-4a6b-9689-ff6ace3d584e\" height=\"1\" width=\"1\" border=\"0\" alt=\"\" style=\"height: 0; width: 0;\" />"
  }
}